madmigration/__init__.py
madmigration/basemigration/__init__.py
madmigration/basemigration/base_migration.py
madmigration/basemigration/mysql_migration.py
madmigration/basemigration/postgresql_migration.py
madmigration/config/__init__.py
madmigration/config/conf.py
madmigration/config/config_schema.py
madmigration/controller.py
madmigration/db_operations/__init__.py
madmigration/db_operations/operations.py
madmigration/errors.py
madmigration/fullmigration/__init__.py
madmigration/fullmigration/full_migration.py
madmigration/fullmigration/postgresql_full_migration.py
madmigration/main.py
madmigration/utils/__init__.py
madmigration/utils/helpers.py
madmigration/utils/logger.py
madmigration-0.1.32.dist-info/entry_points.txt
madmigration-0.1.32.dist-info/LICENSE
madmigration-0.1.32.dist-info/WHEEL
madmigration-0.1.32.dist-info/METADATA
madmigration-0.1.32.dist-info/RECORD
