Metadata-Version: 2.1
Name: madmigration
Version: 0.1.32
Summary: Mad Migration
License: MIT
Author: Hasan
Author-email: hasan.aleeyev@gmail.com
Requires-Python: >=3.7,<4.0
Classifier: License :: OSI Approved :: MIT License
Classifier: Programming Language :: Python :: 3
Classifier: Programming Language :: Python :: 3.7
Classifier: Programming Language :: Python :: 3.8
Classifier: Programming Language :: Python :: 3.9
Classifier: Programming Language :: Python :: 3.10
Classifier: Programming Language :: Python :: 3.11
Requires-Dist: alembic (>=1.8.1,<2.0.0)
Requires-Dist: click (>=8.1.3,<9.0.0)
Requires-Dist: coloredlogs (>=15.0.1,<16.0.0)
Requires-Dist: mysql (>=0.0.3,<0.0.4)
Requires-Dist: psycopg2 (>=2.9.5,<3.0.0)
Requires-Dist: pydantic (>=1.10.2,<2.0.0)
Requires-Dist: pymongo (>=4.3.2,<5.0.0)
Requires-Dist: python-dateutil (>=2.8.2,<3.0.0)
Requires-Dist: pyyaml (>=6.0,<7.0)
Requires-Dist: regex (>=2022.10.31,<2023.0.0)
Requires-Dist: sqlalchemy (>=1.4.44,<2.0.0)
Requires-Dist: sqlalchemy-utils (>=0.38.3,<0.39.0)
